README.md
setup.py
Albot.Online.egg-info/PKG-INFO
Albot.Online.egg-info/SOURCES.txt
Albot.Online.egg-info/dependency_links.txt
Albot.Online.egg-info/top_level.txt
AlbotOnline/AlbotConnection.py
AlbotOnline/GridBoard.py
AlbotOnline/JsonProtocol.py
AlbotOnline/__init__.py
AlbotOnline/BrickPuzzle/BrickPuzzleBoard.py
AlbotOnline/BrickPuzzle/BrickPuzzleGame.py
AlbotOnline/BrickPuzzle/MoveSimulator.py
AlbotOnline/BrickPuzzle/__init__.py
AlbotOnline/Connect4/Connect4Board.py
AlbotOnline/Connect4/Connect4Constants.py
AlbotOnline/Connect4/Connect4Game.py
AlbotOnline/Connect4/__init__.py
AlbotOnline/QueueFlowServiceControl/Simulation.py
AlbotOnline/QueueFlowServiceControl/__init__.py
AlbotOnline/Snake/SnakeBoard.py
AlbotOnline/Snake/SnakeConstants.py
AlbotOnline/Snake/SnakeGame.py
AlbotOnline/Snake/__init__.py
AlbotOnline/TwitterMonteCarlo/Twitter.py
AlbotOnline/TwitterMonteCarlo/__init__.py