Metadata-Version: 1.0
Name: Albot.Online
Version: 0.65
Summary: A simple library for connecting you and supplying game functions for  the Albot.Onlie Client.
Home-page: https://www.albot.online/
Author: Albot.Online
Author-email: Albot.Online.info@gmail.com
License: MIT
Platform: UNKNOWN
